MANIFEST.in
README.rst
setup.cfg
setup.py
test.py
config_provider/__init__.py
config_provider/config_provider.py
config_provider.egg-info/PKG-INFO
config_provider.egg-info/SOURCES.txt
config_provider.egg-info/dependency_links.txt
config_provider.egg-info/requires.txt
config_provider.egg-info/top_level.txt
tests/__init__.py
tests/config_provider_tests.py