Metadata-Version: 1.1
Name: config-provider
Version: 1.0.0
Summary: GBDX Config Provider
Home-page: https://github.com/TDG-Platform/app-config
Author: Various
Author-email: tdgplatform@digitalglobe.com
License: UNKNOWN
Keywords: config,gbdx
Platform: Posix; MacOS X; Windows
Classifier: Development Status :: 3 - Alpha
Classifier: Intended Audience :: Developers
Classifier: License :: Other/Proprietary License
Classifier: Operating System :: OS Independent
Classifier: Topic :: Internet
Classifier: Programming Language :: Python :: 2.7
